zelos_sdk-0.0.8.dist-info/METADATA
zelos_sdk-0.0.8.dist-info/WHEEL
zelos_sdk-0.0.8.dist-info/entry_points.txt
zelos_sdk/__init__.py
zelos_sdk/hooks/logging.py
zelos_sdk/extensions/__init__.py
zelos_sdk/extensions/config.py
zelos_sdk/trace/__init__.py
zelos_sdk/trace/source_cache.py
zelos_sdk/trace/conditions.py
zelos_sdk/_actions.pyi
zelos_sdk/__init__.pyi
zelos_sdk/pytest/plugins/__init__.py
zelos_sdk/pytest/plugins/hooks.py
zelos_sdk/pytest/config/__init__.py
zelos_sdk/pytest/config/hooks.py
zelos_sdk/pytest/__init__.py
zelos_sdk/pytest/report/__init__.py
zelos_sdk/pytest/trace/__init__.py
zelos_sdk/pytest/trace/hooks.py
zelos_sdk/pytest/trace/_logging.py
zelos_sdk/pytest/trace/_file.py
zelos_sdk/pytest/trace/_stdout.py
zelos_sdk/pytest/checker/__init__.py
zelos_sdk/pytest/checker/checker.py
zelos_sdk/pytest/checker/ops.py
zelos_sdk/pytest/checker/items.py
zelos_sdk/core/__init__.py
zelos_sdk/core/context.py
zelos_sdk/mock.pyi
zelos_sdk/actions/fields.py
zelos_sdk/actions/__init__.py
zelos_sdk/actions/core.py
zelos_sdk/actions/types.py
zelos_sdk/actions/discovery.py
zelos_sdk/zelos_sdk.abi3.so
zelos_sdk-0.0.8.dist-info/RECORD
