Metadata-Version: 2.3
Name: zelos-sdk
Version: 0.0.8
Classifier: Programming Language :: Python :: 3
Classifier: License :: Other/Proprietary License
Classifier: Operating System :: OS Independent
Requires-Dist: colorama
Requires-Dist: jsonschema >=4.21.1
Requires-Dist: pytest >=8.1.0
Requires-Dist: rich
Summary: Use the Zelos SDK to push data into the Zelos App, Zelos Agent or directly to Zelos Cloud.
Author-email: Zelos Cloud <info@zeloscloud.io>
Requires-Python: >=3.10
